tdms_reader/__init__.py
tdms_reader/__main__.py
tdms_reader-0.1.11.dist-info/WHEEL
tdms_reader-0.1.11.dist-info/METADATA
tdms_reader-0.1.11.dist-info/RECORD
