Metadata-Version: 2.1
Name: tdms-reader
Version: 0.1.11
Summary: 
Author: mjaquier
Author-email: mjaquier@front.xyz
Requires-Python: >=3.8,<4.0
Classifier: Programming Language :: Python :: 3
Classifier: Programming Language :: Python :: 3.8
Requires-Dist: bokeh (>=2.1.1,<3.0.0)
Requires-Dist: nptdms (>=0.27.0,<0.28.0)
Requires-Dist: pandas (>=1.1.0,<2.0.0)
Requires-Dist: scipy (>=1.5.2,<2.0.0)
Requires-Dist: simplelogging (>=0.10.0,<0.11.0)
